mypkg/calcarea/Calcarea.py
mypkg/calcarea/__init__.py
mypkg/calcc/__init__.py
mypkg/calcc/calcmathes.py
mmypkg-0.1.1.dist-info/METADATA
mmypkg-0.1.1.dist-info/WHEEL
mmypkg-0.1.1.dist-info/entry_points.txt
mmypkg-0.1.1.dist-info/RECORD
